LICENSE
README.md
setup.py
dut_tea/__init__.py
dut_tea/audio.py
dut_tea/stream.py
dut_tea.egg-info/PKG-INFO
dut_tea.egg-info/SOURCES.txt
dut_tea.egg-info/dependency_links.txt
dut_tea.egg-info/requires.txt
dut_tea.egg-info/top_level.txt