Metadata-Version: 2.1
Name: dut-tea
Version: 0.0.1
Summary: Streaming Videos data via networks
Home-page: https://github.com/minhduc1999/dut_tea.git
Author: Dut
Author-email: <mduc221199@gmail.com>
Project-URL: Source, https://github.com/minhduc1999/dut_tea.git
Keywords: python,video,stream,video stream,camera stream,sockets
Classifier: Development Status :: 1 - Planning
Classifier: Intended Audience :: Developers
Classifier: Programming Language :: Python :: 3
Classifier: Operating System :: Unix
Classifier: Operating System :: MacOS :: MacOS X
Classifier: Operating System :: Microsoft :: Windows
License-File: LICENSE
